{
  "$schema": "https://mintlify.com/docs.json",
  "theme": "maple",
  "name": "collony docs",
  "description": "collony AI — Telegram & Discord community moderator docs.",
  "colors": {
    "primary": "#F4A700",
    "light": "#FFE9A8",
    "dark": "#111111"
  },
  "favicon": "/public/favicon.png",
  "logo": "/public/logo.png",
  "navigation": {
    "groups": [
      {
        "group": "Setup",
        "pages": [
          "before_you_start",
          "prepare-your-telegram-group",
          "find-collony-ai-on-telegram",
          "add-collony-to-your-group"
        ]
      },
      {
        "group": "Customize",
        "pages": [
          "in-bot-setup-menu",
          "add-project-description",
          "add-project-knowledge-base",
          "set-community-moderation-rules",
          "set-community-mod-personality"
        ]
      },
      {
        "group": "Manage",
        "pages": [
          "manage-admins-and-moderators",
          "setup-the-admin-dashboard-chat"
        ]
      }
    ]
  },
  "footer": {
    "socials": {
      "x": "https://x.com/collonyai",
      "telegram": "https://t.me/collonyai",
      "linkedin": "https://www.linkedin.com/company/collony",
      "website": "https://collony.ai"
    }
  }
}